dataultractl/__init__.py
dataultractl/undeploycommands.py
dataultractl/statiscommands.py
dataultractl/stopcommands.py
dataultractl/lscommands.py
dataultractl/client.py
dataultractl/shell.py
dataultractl/removecommands.py
dataultractl/deletecommands.py
dataultractl/deploycommands.py
dataultractl/startcommands.py
dataultractl/addcommands.py
dataultractl/v3_0/__init__.py
dataultractl/v3_0/commonnode.py
dataultractl/v3_0/application.py
dataultractl/v3_0/task.py
dataultractl/v3_0/service.py
dataultractl/v3_0/cluster.py
dataultractl/v3_0/httpclient.py
dataultractl/v3_0/instance.py
dataultractl/v3_0/microservice.py
dataultractl/utils/__init__.py
dataultractl/utils/parse_utils.py
dataultractl/utils/common_utils.py
dataultractl/utils/env_utils.py
dataultractl/utils/https_utils.py
dataultractl/utils/http_utils.py
ductl-1.0.dist-info/WHEEL
ductl-1.0.dist-info/RECORD
ductl-1.0.dist-info/top_level.txt
ductl-1.0.dist-info/METADATA
ductl-1.0.dist-info/zip-safe
ductl-1.0.dist-info/DESCRIPTION.rst
ductl-1.0.dist-info/entry_points.txt
ductl-1.0.dist-info/metadata.json
